.travis.yml
LICENSE.txt
MANIFEST.in
README.rst
pyproject.toml
setup.py
cyarray/__init__.py
cyarray/api.py
cyarray/carray.pxd
cyarray/carray.pxd.mako
cyarray/carray.pyx
cyarray/carray.pyx.mako
cyarray/generator.py
cyarray.egg-info/PKG-INFO
cyarray.egg-info/SOURCES.txt
cyarray.egg-info/dependency_links.txt
cyarray.egg-info/not-zip-safe
cyarray.egg-info/requires.txt
cyarray.egg-info/top_level.txt
cyarray/tests/__init__.py
cyarray/tests/test_carray.py
docs/make.bat
docs/source/conf.py
docs/source/index.rst
docs/source/overview.rst
docs/source/reference/carray.rst
docs/source/reference/index.rst