Metadata-Version: 2.4
Name: cyarray
Version: 1.2
Summary: A fast, typed, resizable, Cython array.
Home-page: http://github.com/pypr/cyarray
Author: Cyarray Developers
Author-email: Cyarray Developers <pysph-dev@googlegroups.com>
License: Unless otherwise specified by LICENSE.txt files in individual
Keywords: Cython,array,resizable
Platform: Linux
Platform: Mac OS-X
Platform: Unix
Platform: Windows
Classifier: Development Status :: 5 - Production/Stable
Classifier: Environment :: Console
Classifier: Intended Audience :: Developers
Classifier: Intended Audience :: Science/Research
Classifier: License :: OSI Approved :: BSD License
Classifier: Natural Language :: English
Classifier: Operating System :: MacOS :: MacOS X
Classifier: Operating System :: Microsoft :: Windows
Classifier: Operating System :: POSIX
Classifier: Operating System :: Unix
Classifier: Programming Language :: Python
Classifier: Programming Language :: Python :: 3
Classifier: Topic :: Scientific/Engineering
Classifier: Topic :: Scientific/Engineering :: Physics
Classifier: Topic :: Software Development :: Libraries
License-File: LICENSE.txt
Requires-Dist: numpy
Provides-Extra: docs
Requires-Dist: sphinx; extra == "docs"
Provides-Extra: tests
Requires-Dist: pytest; extra == "tests"
Requires-Dist: pytest-benchmark[histogram]; extra == "tests"
Provides-Extra: dev
Requires-Dist: sphinx; extra == "dev"
Requires-Dist: pytest; extra == "dev"
Requires-Dist: pytest-benchmark[histogram]; extra == "dev"
Requires-Dist: cython; extra == "dev"
Dynamic: author
Dynamic: home-page
Dynamic: license-file
Dynamic: platform
